ricardo_crawler.py
setup.py
controllers/__init__.py
controllers/http_links_collector.py
controllers/url_content_retrieve.py
ricardo_crawler.egg-info/PKG-INFO
ricardo_crawler.egg-info/SOURCES.txt
ricardo_crawler.egg-info/dependency_links.txt
ricardo_crawler.egg-info/requires.txt
ricardo_crawler.egg-info/top_level.txt
scrapitems/__init__.py
scrapitems/scarp_item.py
test/__init__.py
test/controllers/TestHttpLinksCollector.py
test/controllers/TestUrlContentRetrieve.py
test/controllers/__init__.py