Metadata-Version: 1.1
Name: ricardo-crawler
Version: 01.00.01
Summary: My first Web Scrapper in Python
Home-page: https://github.com/ricardogarfe/crawler-mswl
Author: Ricardo García Fernández
Author-email: ricardogarfe@gmail.com
License: GNU GPLv3
Download-URL: https://github.com/ricardogarfe/crawler-mswl/zipball/v01.00.01
Keywords: web-crawler
Platform: UNKNOWN
